{
  "title": "Chiefs (Recognition) (No. 7) Order, 2003",
  "year": "2003",
  "date": "2003-05-09",
  "language": "en",
  "content": "Suppletmtoeh Rneet p uob(lZaimcGb oivearn ment\nGazdetattFeer di 9dtaMhya. y2 .0 03\nSTATUTINOSRTYR UMENNoT4 .5O F 2 003\nThCeh iAecfts\n(LaVwosl,u1 m6Ce,a 2p8.7 )\nThCeh i(Reefcso gn(Niot7).Oi rodn2e)0r 0,3\nWHEREAtSh Per esiissda etnitts hfitaehtpde e rnsaomnie tndh e\nSchetdtouh Oliresd i eesrn ttihoto lthleedd_ osffipceecth iefireaedsi n\nrequbiysr uebds e(c2ot)sfi e octnih oronthef ee C hiAecfts:\nNoTwHE REFOiREen,x erocfthi eps oew ceornst iasnie ncettidho rne e\notfh Ceh iAecfthtse,fo lloOwridniehgsre rmeabdye :\nI.T hOir_dsbe ceri attseh dCe h i(Reefcso gni(tNi7ooO).nr )d eTrit,l e\n2003.\n2.T hpee rsnoanm iethndeS cheidhsue lrreee bcyo gnabises ienRdeg c ognition\nwitthhaiern ie Znaa mdbeisac irtnih Sbece hde tdhuhelo elo,dft e hreo fC hief\nofficsep eciitnfih Seecd h edule.\nSCHEDULE\n(Para2r)a ph\nOffice Area HolodOffifec re\nChieftKauicnheesksa NyabiyeK akuMhauh oNngguon du\noft hLeu vPaeloeop fl e\nZambDeizsiti trnhi ec t\nNorWtehs tPerrno vince\nLEVYP.MWANAWASASC,\nLUSAKA President\n30thA2p0r0i3l ,\n[CHF.6}/21]\nCopioejst Sthaitsu Itnosryt rcuabmneoe bntta firnotemhGd eo verln'mreinntt er,\nP.OB.o 3x0 1J3O6J,LO u/s,aP kar,i ceK500each.\n230 StatIunsttorurym ent 9tMha y2,0 03",
  "source": "https://zambialii.org/akn/zm/act/si/2003/45/eng@2003-05-09",
  "type": "act",
  "related_files": [
    {
      "type": "pdf",
      "url": "https://zambialii.org/akn/zm/act/si/2003/45/eng@2003-05-09/source.pdf",
      "path": "lawdata\\zm_act_si_2003_45_eng@2003-05-09\\zm_act_si_2003_45_eng_2003-05-09.pdf"
    }
  ],
  "citations": []
}